simplech/__init__.py
simplech/simplech.py
simplech-0.1.1.dist-info/DESCRIPTION.rst
simplech-0.1.1.dist-info/METADATA
simplech-0.1.1.dist-info/RECORD
simplech-0.1.1.dist-info/WHEEL
simplech-0.1.1.dist-info/metadata.json
simplech-0.1.1.dist-info/top_level.txt
