Metadata-Version: 2.0
Name: simplech
Version: 0.1.1
Summary: Simple ClickHouse client that uses json as main format
Home-page: https://github.com/madiedinro
Author: Dmitry Rodin
Author-email: madiedinro@gmail.com
License: MIT
Project-URL: Homepage, https://github.com/madiedinro
Platform: UNKNOWN
Classifier: Development Status :: 3 - Alpha
Classifier: License :: OSI Approved :: MIT License
Classifier: Programming Language :: Python :: 3.5
Classifier: Programming Language :: Python :: 3.6
Requires-Dist: ujson
